{
  "pilotos": [
    {
      "id": "1",
      "nombre": "Max",
      "apellido": "Verstappen",
      "edad": 27,
      "nacionalidad": "Países Bajos",
      "equipo": "Red Bull Racing",
      "debut": 2015,
      "titulos": 3
    },
    {
      "id": "2",
      "nombre": "Lewis",
      "apellido": "Hamilton",
      "edad": 40,
      "nacionalidad": "Reino Unido",
      "equipo": "Mercedes",
      "debut": 2007,
      "titulos": 7
    },
    {
      "id": "3",
      "nombre": "Charles",
      "apellido": "Leclerc",
      "edad": 27,
      "nacionalidad": "Mónaco",
      "equipo": "Ferrari",
      "debut": 2018,
      "titulos": 0
    },
    {
      "id": "4",
      "nombre": "Lando",
      "apellido": "Norris",
      "edad": 25,
      "nacionalidad": "Reino Unido",
      "equipo": "McLaren",
      "debut": 2019,
      "titulos": 0
    },
    {
      "id": "5",
      "nombre": "Fernando",
      "apellido": "Alonso",
      "edad": 44,
      "nacionalidad": "España",
      "equipo": "Aston Martin",
      "debut": 2001,
      "titulos": 2
    }
  ],
  "circuitos": [
    {
      "id": "1",
      "nombre": "Circuit de Spa-Francorchamps",
      "ubicacion": "Stavelot",
      "pais": "Bélgica",
      "vueltas": 44,
      "longitud_km": 7.004
    },
    {
      "id": "2",
      "nombre": "Hungaroring",
      "ubicacion": "Mogyoród",
      "pais": "Hungría",
      "vueltas": 70,
      "longitud_km": 4.381
    },
    {
      "id": "3",
      "nombre": "Silverstone Circuit",
      "ubicacion": "Silverstone",
      "pais": "Reino Unido",
      "vueltas": 52,
      "longitud_km": 5.891
    }
  ],
  "ranking": [
    {
      "id": "1",
      "nombre": "Lucas Fernández",
      "puntos": 128,
      "piloto_favorito": "Max Verstappen",
      "pais": "Argentina"
    },
    {
      "id": "2",
      "nombre": "Martina López",
      "puntos": 115,
      "piloto_favorito": "Charles Leclerc",
      "pais": "Uruguay"
    },
    {
      "id": "3",
      "nombre": "Diego Ramírez",
      "puntos": 109,
      "piloto_favorito": "Lando Norris",
      "pais": "Chile"
    },
    {
      "id": "4",
      "nombre": "Valentina Torres",
      "puntos": 102,
      "piloto_favorito": "Fernando Alonso",
      "pais": "México"
    },
    {
      "id": "5",
      "nombre": "Matías Gómez",
      "puntos": 97,
      "piloto_favorito": "Lewis Hamilton",
      "pais": "Colombia"
    }
  ],
  "escuderias": [
    {
      "id": "1",
      "nombre": "Red Bull Racing",
      "pais_base": "Reino Unido",
      "jefe_equipo": "Christian Horner",
      "motor": "Honda RBPT"
    },
    {
      "id": "2",
      "nombre": "Mercedes-AMG Petronas",
      "pais_base": "Reino Unido",
      "jefe_equipo": "Toto Wolff",
      "motor": "Mercedes"
    },
    {
      "id": "3",
      "nombre": "Scuderia Ferrari",
      "pais_base": "Italia",
      "jefe_equipo": "Frédéric Vasseur",
      "motor": "Ferrari"
    },
    {
      "id": "4",
      "nombre": "McLaren F1 Team",
      "pais_base": "Reino Unido",
      "jefe_equipo": "Andrea Stella",
      "motor": "Mercedes"
    },
    {
      "id": "5",
      "nombre": "Aston Martin Aramco",
      "pais_base": "Reino Unido",
      "jefe_equipo": "Mike Krack",
      "motor": "Mercedes"
    },
    {
      "id": "6",
      "nombre": "Alpine F1 Team",
      "pais_base": "Francia",
      "jefe_equipo": "Bruno Famin",
      "motor": "Renault"
    },
    {
      "id": "7",
      "nombre": "Visa Cash App RB F1 Team",
      "pais_base": "Italia",
      "jefe_equipo": "Laurent Mekies",
      "motor": "Honda RBPT"
    },
    {
      "id": "8",
      "nombre": "Stake F1 Team Kick Sauber",
      "pais_base": "Suiza",
      "jefe_equipo": "Alessandro Alunni Bravi",
      "motor": "Ferrari",
      "paisBase": "Suiza",
      "jefeEquipo": "Alessandro Alunni Bravi"
    },
    {
      "id": "9",
      "nombre": "Williams Racing",
      "pais_base": "Reino Unido",
      "jefe_equipo": "James Vowles",
      "motor": "Mercedes"
    },
    {
      "id": "10",
      "nombre": "Haas F1 Team",
      "pais_base": "Estados Unidos",
      "jefe_equipo": "Ayao Komatsu",
      "motor": "Ferrari"
    }
  ],
  "usuarios": [
    {
      "id": "1",
      "nombre": "admin",
      "email": "admin@admin.com",
      "password": "admin123",
      "telefono": "",
      "rol": "admin"
    },
    {
      "id": "2",
      "nombre": "user",
      "email": "user@user.com",
      "password": "user123",
      "telefono": "6143123123",
      "rol": "user"
    }
  ],
  "carreras": [
    {
      "id": 1,
      "nombre": "Gran Premio de Bahréin",
      "fechaCarrera": "2025-03-01",
      "horaCarrera": "14:00",
      "circuito": {
        "id": 1,
        "nombre": "Circuito Internacional de Sakhir",
        "ubicacion": "Sakhir",
        "pais": "Baréin",
        "vueltas": 57,
        "longitud_km": 5.412
      },
      "pilotos": [
        { "id": 1, "nombre": "Max Verstappen", "escuderia": "Red Bull" },
        { "id": 2, "nombre": "Sergio Pérez", "escuderia": "Red Bull" },
        { "id": 3, "nombre": "Lewis Hamilton", "escuderia": "Mercedes" },
        { "id": 4, "nombre": "Charles Leclerc", "escuderia": "Ferrari" },
        { "id": 5, "nombre": "Carlos Sainz", "escuderia": "Ferrari" }
      ],
      "resultados": [
        { "posicion": 1, "idPiloto": 1, "nombre": "Max Verstappen", "escuderia": "Red Bull" },
        { "posicion": 2, "idPiloto": 4, "nombre": "Charles Leclerc", "escuderia": "Ferrari"},
        { "posicion": 3, "idPiloto": 3, "nombre": "Lewis Hamilton", "escuderia": "Mercedes" }
      ]
    },
    {
      "id": 2,
      "nombre": "Gran Premio de Arabia Saudita",
      "fechaCarrera": "2025-03-15",
      "horaCarrera": "18:00",
      "circuito": {
        "id": 2,
        "nombre": "Circuito de Jeddah",
        "ubicacion": "Jeddah",
        "pais": "Arabia Saudita",
        "vueltas": 50,
        "longitud_km": 6.174
      },
      "pilotos": [
        { "id": 1, "nombre": "Max Verstappen", "escuderia": "Red Bull" },
        { "id": 2, "nombre": "Sergio Pérez", "escuderia": "Red Bull" },
        { "id": 3, "nombre": "Lewis Hamilton", "escuderia": "Mercedes" },
        { "id": 4, "nombre": "Charles Leclerc", "escuderia": "Ferrari" },
        { "id": 5, "nombre": "Fernando Alonso", "escuderia": "Aston Martin" }
      ],
      "resultados": []
    },
    {
      "id": 3,
      "nombre": "Gran Premio de Australia",
      "fechaCarrera": "2025-04-05",
      "horaCarrera": "07:00",
      "circuito": {
        "id": 3,
        "nombre": "Albert Park",
        "ubicacion": "Melbourne",
        "pais": "Australia",
        "vueltas": 58,
        "longitud_km": 5.303
      },
      "pilotos": [
        { "id": 1, "nombre": "Max Verstappen", "escuderia": "Red Bull" },
        { "id": 3, "nombre": "Lewis Hamilton", "escuderia": "Mercedes" },
        { "id": 4, "nombre": "Charles Leclerc", "escuderia": "Ferrari" },
        { "id": 5, "nombre": "Fernando Alonso", "escuderia": "Aston Martin" },
        { "id": 6, "nombre": "Lando Norris", "escuderia": "McLaren" }
      ],
      "resultados": []
    },
    {
      "id": 4,
      "nombre": "Gran Premio de Japón",
      "fechaCarrera": "2025-05-19",
      "horaCarrera": "02:00",
      "circuito": {
        "id": 4,
        "nombre": "Suzuka Circuit",
        "ubicacion": "Suzuka",
        "pais": "Japón",
        "vueltas": 53,
        "longitud_km": 5.807
      },
      "pilotos": [],
      "resultados": []
    },
    {
      "id": 5,
      "nombre": "Gran Premio de China",
      "fechaCarrera": "2025-06-26",
      "horaCarrera": "09:00",
      "circuito": {
        "id": 5,
        "nombre": "Shanghai International Circuit",
        "ubicacion": "Shanghai",
        "pais": "China",
        "vueltas": 56,
        "longitud_km": 5.451
      },
      "pilotos": [],
      "resultados": []
    },
    {
      "id": 6,
      "nombre": "Gran Premio de Miami",
      "fechaCarrera": "2025-07-10",
      "horaCarrera": "16:30",
      "circuito": {
        "id": 6,
        "nombre": "Miami International Autodrome",
        "ubicacion": "Miami",
        "pais": "Estados Unidos",
        "vueltas": 57,
        "longitud_km": 5.412
      },
      "pilotos": [],
      "resultados": []
    },
    {
      "id": 7,
      "nombre": "Gran Premio de Emilia-Romaña",
      "fechaCarrera": "2025-08-28",
      "horaCarrera": "09:00",
      "circuito": {
        "id": 7,
        "nombre": "Autodromo Enzo e Dino Ferrari",
        "ubicacion": "Imola",
        "pais": "Italia",
        "vueltas": 63,
        "longitud_km": 4.909
      },
      "pilotos": [],
      "resultados": []
    },
    {
      "id": 8,
      "nombre": "Gran Premio de Mónaco",
      "fechaCarrera": "2025-09-24",
      "horaCarrera": "09:00",
      "circuito": {
        "id": 8,
        "nombre": "Circuit de Monaco",
        "ubicacion": "Montecarlo",
        "pais": "Mónaco",
        "vueltas": 78,
        "longitud_km": 3.337
      },
      "pilotos": [],
      "resultados": []
    },
    {
      "id": 9,
      "nombre": "Gran Premio de Canadá",
      "fechaCarrera": "2025-10-07",
      "horaCarrera": "15:00",
      "circuito": {
        "id": 9,
        "nombre": "Circuit Gilles Villeneuve",
        "ubicacion": "Montreal",
        "pais": "Canadá",
        "vueltas": 70,
        "longitud_km": 4.361
      },
      "pilotos": [],
      "resultados": []
    },
    {
      "id": 10,
      "nombre": "Gran Premio de España",
      "fechaCarrera": "2025-11-21",
      "horaCarrera": "09:00",
      "circuito": {
        "id": 10,
        "nombre": "Circuit de Barcelona-Catalunya",
        "ubicacion": "Montmeló",
        "pais": "España",
        "vueltas": 66,
        "longitud_km": 4.675
      },
      "pilotos": [],
      "resultados": []
    }
  ]
}